[{"ingredient_id":1665,"supply_ingredient_num":5,"supply_ingredient_sum":52500,"supply_ingredient_sum_netto":52500,"ingredient_name":"Насадка на швабру","ingredient_unit":"p","tax_id":0},{"ingredient_id":2018,"supply_ingredient_num":5,"supply_ingredient_sum":79000,"supply_ingredient_sum_netto":79000,"ingredient_name":"Корзина 23 л","ingredient_unit":"p","tax_id":0},{"ingredient_id":2017,"supply_ingredient_num":10,"supply_ingredient_sum":19500,"supply_ingredient_sum_netto":19500,"ingredient_name":"Палиця для швабри","ingredient_unit":"p","tax_id":0},{"ingredient_id":1918,"supply_ingredient_num":14,"supply_ingredient_sum":121100,"supply_ingredient_sum_netto":121100,"ingredient_name":"Контейнер пластиковий 17 л","ingredient_unit":"p","tax_id":0},{"ingredient_id":2019,"supply_ingredient_num":1,"supply_ingredient_sum":3900,"supply_ingredient_sum_netto":3900,"ingredient_name":"Відро","ingredient_unit":"p","tax_id":0}]