[{"ingredient_id":1637,"supply_ingredient_num":60,"supply_ingredient_sum":243000,"supply_ingredient_sum_netto":243000,"ingredient_name":"Пакет для сміття 120л (по рулонах)","ingredient_unit":"p","tax_id":0},{"ingredient_id":1639,"supply_ingredient_num":50,"supply_ingredient_sum":108000,"supply_ingredient_sum_netto":108000,"ingredient_name":"Пакет для сміття 60л (по рулонах)","ingredient_unit":"p","tax_id":0},{"ingredient_id":1638,"supply_ingredient_num":50,"supply_ingredient_sum":97500,"supply_ingredient_sum_netto":97500,"ingredient_name":"Пакет для сміття  35л (по рулонах)","ingredient_unit":"p","tax_id":0},{"ingredient_id":1644,"supply_ingredient_num":30,"supply_ingredient_sum":2280000,"supply_ingredient_sum_netto":2280000,"ingredient_name":"Плівка  ПВХ 450*1000 (поштучно)","ingredient_unit":"p","tax_id":0},{"ingredient_id":1653,"supply_ingredient_num":144,"supply_ingredient_sum":98400,"supply_ingredient_sum_netto":98400,"ingredient_name":"Туалетний папір \"Кохавинка\" (поштучно)","ingredient_unit":"p","tax_id":0},{"ingredient_id":1642,"supply_ingredient_num":9000,"supply_ingredient_sum":885000,"supply_ingredient_sum_netto":885000,"ingredient_name":"Піддон М3-20 Білий (уп/300шт) (поштучно)","ingredient_unit":"p","tax_id":0},{"ingredient_id":1616,"supply_ingredient_num":5,"supply_ingredient_sum":28000,"supply_ingredient_sum_netto":28000,"ingredient_name":"Білизна 5л (поштучно)","ingredient_unit":"p","tax_id":0}]